config_mgmt_server/__init__.py
config_mgmt_server/asgi.py
config_mgmt_server/settings.py
config_mgmt_server/urls.py
config_mgmt_server/wsgi.py
config_mgmt_server/app/__init__.py
config_mgmt_server/app/admin.py
config_mgmt_server/app/apps.py
config_mgmt_server/app/models.py
config_mgmt_server/app/serializers.py
config_mgmt_server/app/tests.py
config_mgmt_server/app/urls.py
config_mgmt_server/app/views.py
config_mgmt_server-1.0.18.dist-info/LICENSE.txt
config_mgmt_server-1.0.18.dist-info/METADATA
config_mgmt_server-1.0.18.dist-info/WHEEL
config_mgmt_server-1.0.18.dist-info/entry_points.txt
config_mgmt_server-1.0.18.dist-info/top_level.txt
config_mgmt_server-1.0.18.dist-info/RECORD
