Metadata-Version: 2.1
Name: config-mgmt-server
Version: 1.0.18
Summary: Suncoast Systems Core Router Config Mgmt Server
Author-email: Suncoast Systems <administrator@suncoast.systems>
Maintainer-email: Dotcom Row <dotcom.row@gmail.com>
License: This project is only for Dotcom Row services, no other use is allowed or even possible!
Project-URL: Homepage, https://github.com/pypa/sampleproject
Project-URL: Bug Reports, https://github.com/pypa/sampleproject/issues
Project-URL: Funding, https://donate.pypi.org
Project-URL: Say Thanks!, http://saythanks.io/to/example
Project-URL: Source, https://github.com/pypa/sampleproject/
Keywords: config,suncoast systems,router
Classifier: Development Status :: 3 - Alpha
Classifier: Topic :: System :: Operating System Kernels :: BSD
Classifier: License :: OSI Approved :: MIT License
Classifier: Programming Language :: Python :: 3.7
Requires-Python: >=3.7
License-File: LICENSE.txt
Requires-Dist: python-daemon
Requires-Dist: flask
Requires-Dist: celery
Provides-Extra: dev
Requires-Dist: check-manifest ; extra == 'dev'
Provides-Extra: test
Requires-Dist: coverage ; extra == 'test'
